imageprobe/__init__.py
imageprobe/client.py
imageprobe/errors.py
imageprobe/parser.py
imageprobe/parsers/__init__.py
imageprobe/parsers/gif.py
imageprobe/parsers/png.py
imageprobe/py.typed
imageprobe/types.py
imageprobe-0.3.0.dist-info/LICENSE
imageprobe-0.3.0.dist-info/WHEEL
imageprobe-0.3.0.dist-info/METADATA
imageprobe-0.3.0.dist-info/RECORD
