Metadata-Version: 2.1
Name: imageprobe
Version: 0.3.0
Summary: Asynchronous image probing library. Fetch only as much as you need!
Home-page: http://github.com/palt0/imageprobe
License: MIT
Keywords: imagesize,fastimage
Author: Plato
Author-email: platoo@outlook.it
Requires-Python: >=3.6.2,<4.0.0
Classifier: Development Status :: 3 - Alpha
Classifier: Intended Audience :: Developers
Classifier: License :: OSI Approved :: MIT License
Classifier: Operating System :: OS Independent
Classifier: Programming Language :: Python :: 3
Classifier: Programming Language :: Python :: 3.10
Classifier: Programming Language :: Python :: 3.6
Classifier: Programming Language :: Python :: 3.7
Classifier: Programming Language :: Python :: 3.8
Classifier: Programming Language :: Python :: 3.9
Classifier: Topic :: Multimedia :: Graphics
Classifier: Topic :: Software Development :: Libraries :: Python Modules
Classifier: Typing :: Typed
Requires-Dist: aiohttp (>=3.7.3,<4.0.0)
Requires-Dist: dataclasses (>=0.7,<0.8); python_full_version >= "3.6.2" and python_full_version < "3.7.0"
Project-URL: Repository, http://github.com/palt0/imageprobe
